walletpay/__init__.py
walletpay/client/__init__.py
walletpay/client/client.py
walletpay/client/session/__init__.py
walletpay/client/session/_aiohttp.py
walletpay/client/session/base.py
walletpay/exceptions.py
walletpay/methods/__init__.py
walletpay/methods/base.py
walletpay/methods/create.py
walletpay/methods/get_order_amount.py
walletpay/methods/get_order_list.py
walletpay/methods/get_preview.py
walletpay/types/__init__.py
walletpay/types/base.py
walletpay/types/create_response.py
walletpay/types/enums.py
walletpay/types/get_preview_response.py
walletpay/types/money_amount.py
walletpay/types/order_amount.py
walletpay/types/order_list.py
walletpay/types/order_preview.py
walletpay/types/order_reconciliation_item.py
walletpay/types/payment_option.py
walletpay/types/update.py
walletpay_sdk-1.1.3.dist-info/METADATA
walletpay_sdk-1.1.3.dist-info/WHEEL
walletpay_sdk-1.1.3.dist-info/RECORD
