Metadata-Version: 2.1
Name: walletpay-sdk
Version: 1.1.3
Summary: 
Author: pypchuk
Author-email: opengl32.dll.tar.gz@gmail.com
Requires-Python: >=3.11,<4.0
Classifier: Programming Language :: Python :: 3
Classifier: Programming Language :: Python :: 3.11
Requires-Dist: adaptix (>=3.0.0a4,<4.0.0)
Requires-Dist: aiohttp (>=3.8.5,<4.0.0)
